st_tiny_editor/__init__.py
st_tiny_editor/example.py
st_tiny_editor/frontend/build/asset-manifest.json
st_tiny_editor/frontend/build/bootstrap.min.css
st_tiny_editor/frontend/build/index.html
st_tiny_editor/frontend/build/static/js/main.0058a8af.js
st_tiny_editor/frontend/build/static/js/main.0058a8af.js.LICENSE.txt
st_tiny_editor/frontend/build/static/js/main.0058a8af.js.map
st_tiny_editor-1.0.3.dist-info/LICENSE
st_tiny_editor-1.0.3.dist-info/METADATA
st_tiny_editor-1.0.3.dist-info/WHEEL
st_tiny_editor-1.0.3.dist-info/top_level.txt
st_tiny_editor-1.0.3.dist-info/RECORD
