Metadata-Version: 2.1
Name: st-tiny-editor
Version: 1.0.3
Summary: Streamlit component that allows you to render a TinyMCE editor in your app.
Home-page: UNKNOWN
Author: Sergio Demis Lopez Martinez
Author-email: sergioska81@hotmail.com
License: UNKNOWN
Platform: UNKNOWN
Requires-Python: >=3.7
Requires-Dist: streamlit >=0.63
Provides-Extra: devel
Requires-Dist: wheel ; extra == 'devel'
Requires-Dist: pytest ==7.4.0 ; extra == 'devel'
Requires-Dist: playwright ==1.39.0 ; extra == 'devel'
Requires-Dist: requests ==2.31.0 ; extra == 'devel'
Requires-Dist: pytest-playwright-snapshot ==1.0 ; extra == 'devel'
Requires-Dist: pytest-rerunfailures ==12.0 ; extra == 'devel'
